lvmnps/__init__.py
lvmnps/__main__.py
lvmnps/exceptions.py
lvmnps/tools.py
lvmnps/actor/__init__.py
lvmnps/actor/actor.py
lvmnps/actor/schema.json
lvmnps/actor/commands/__init__.py
lvmnps/actor/commands/onoff.py
lvmnps/actor/commands/refresh.py
lvmnps/actor/commands/scripts.py
lvmnps/actor/commands/status.py
lvmnps/nps/__init__.py
lvmnps/nps/core.py
lvmnps/nps/implementations/__init__.py
lvmnps/nps/implementations/dli.py
lvmnps/nps/implementations/netio.py
sdss_lvmnps-1.2.1.dist-info/METADATA
sdss_lvmnps-1.2.1.dist-info/WHEEL
sdss_lvmnps-1.2.1.dist-info/entry_points.txt
sdss_lvmnps-1.2.1.dist-info/licenses/LICENSE.md
sdss_lvmnps-1.2.1.dist-info/RECORD
