Metadata-Version: 2.4
Name: sdss-lvmnps
Version: 1.2.1
Summary: A library and actor to communicate with an SDSS-V LVM network power switch
Project-URL: Homepage, https://github.com/sdss/lvmnps
Project-URL: Repository, https://github.com/sdss/lvmnps
Project-URL: Documentation, https://lvmnps.readthedocs.org
Author-email: Florian Briegel <briegel@mpia.de>, José Sánchez-Gallego <gallegoj@uw.edu>, Changgon Kim <changgonkim@khu.ac.kr>, Mingyeong Yang <mingyeong@khu.ac.kr>
License-Expression: BSD-3-Clause
License-File: LICENSE.md
Requires-Python: <4.0,>=3.10
Requires-Dist: click-default-group>=1.2.2
Requires-Dist: httpx>=0.28.1
Requires-Dist: lvmopstools>=0.5.18
Requires-Dist: pydantic>=2.5.2
Requires-Dist: sdss-clu>=2.4.3
Requires-Dist: sdsstools>=1.9.1
